bootstrap.py
buildout.cfg
run.sh
server.ini
setup.cfg
setup.py
docs/Makefile
docs/make.bat
docs/source/HISTORY.rst
docs/source/README.rst
docs/source/conf.py
docs/source/index.rst
zopyx/__init__.py
zopyx.smartprintng.server.egg-info/PKG-INFO
zopyx.smartprintng.server.egg-info/SOURCES.txt
zopyx.smartprintng.server.egg-info/dependency_links.txt
zopyx.smartprintng.server.egg-info/entry_points.txt
zopyx.smartprintng.server.egg-info/namespace_packages.txt
zopyx.smartprintng.server.egg-info/not-zip-safe
zopyx.smartprintng.server.egg-info/requires.txt
zopyx.smartprintng.server.egg-info/top_level.txt
zopyx/smartprintng/__init__.py
zopyx/smartprintng/server/__init__.py
zopyx/smartprintng/server/configure.zcml
zopyx/smartprintng/server/header.txt
zopyx/smartprintng/server/logger.py
zopyx/smartprintng/server/mail_util.py
zopyx/smartprintng/server/models.py
zopyx/smartprintng/server/nullauth.py
zopyx/smartprintng/server/run.py
zopyx/smartprintng/server/tests.py
zopyx/smartprintng/server/views.py
zopyx/smartprintng/server/templates/index.pt
zopyx/smartprintng/server/templates/static/default.css
zopyx/smartprintng/server/templates/static/zopyx_logo.png
zopyx/smartprintng/server/test_data/test.html
zopyx/smartprintng/server/test_data/test.zip