Metadata-Version: 1.0
Name: zopyx.smartprintng.server
Version: 1.1.1
Summary: ZOPYX SmartPrintNG Server
Home-page: http://www.zopyx.com/projects/smartprintng
Author: Andreas Jung
Author-email: info@zopyx.com
License: ZPL
Keywords: SmartPrintNG Conversion Pyramid
Platform: UNKNOWN
Classifier: Programming Language :: Python
Classifier: Topic :: Software Development :: Libraries :: Python Modules
